errorhelpers/__init__.py
errorhelpers-0.2.0.dist-info/LICENSE
errorhelpers-0.2.0.dist-info/WHEEL
errorhelpers-0.2.0.dist-info/METADATA
errorhelpers-0.2.0.dist-info/RECORD
