Metadata-Version: 2.1
Name: errorhelpers
Version: 0.2.0
Summary: Helpers for handling Python errors
Home-page: https://github.com/sayanarijit/errorhelpers
License: MIT
Keywords: error,helpers
Author: Arijit Basu
Author-email: sayanarijit@gmail.com
Requires-Python: >=3.6,<4.0
Classifier: License :: OSI Approved :: MIT License
Classifier: Programming Language :: Python :: 3
Classifier: Programming Language :: Python :: 3.6
Classifier: Programming Language :: Python :: 3.7
Classifier: Programming Language :: Python :: 3.8
Classifier: Programming Language :: Python :: 3.9
Requires-Dist: typing-extensions (>=3.7.4,<4.0.0)
